{
  "max_freq_019": {
    "alpha": "1/2",
    "beta_0_8": 0,
    "beta_0_9": 0,
    "beta_1_8": 0,
    "beta_1_9": 0,
    "beta_2_8": 0,
    "beta_2_9": "1/2",
    "beta_3_8": 0,
    "beta_3_9": "1/2",
    "beta_4_8": 0,
    "beta_4_9": "1/2",
    "beta_5_8": 0,
    "beta_5_9": "1/2",
    "beta_6_8": 0,
    "beta_6_9": "1/2",
    "beta_7_8": 0,
    "beta_7_9": "1/2",
    "gamma": "1/2"
  },
  "min_freq_019": {
    "alpha": "5/2",
    "beta_0_8": 0,
    "beta_0_9": 0,
    "beta_1_8": 0,
    "beta_1_9": 0,
    "beta_2_8": "5/2",
    "beta_2_9": 0,
    "beta_3_8": "5/2",
    "beta_3_9": 0,
    "beta_4_8": "3/2",
    "beta_4_9": "1/1",
    "beta_5_8": 0,
    "beta_5_9": "5/2",
    "beta_6_8": 0,
    "beta_6_9": "5/2",
    "beta_7_8": "5/2",
    "beta_7_9": 0,
    "gamma": "11/2"
  },
  "max_freq_018": {
    "alpha": "1/2",
    "beta_0_8": 0,
    "beta_0_9": 0,
    "beta_1_8": 0,
    "beta_1_9": 0,
    "beta_2_8": "1/2",
    "beta_2_9": 0,
    "beta_3_8": "1/2",
    "beta_3_9": 0,
    "beta_4_8": "1/2",
    "beta_4_9": 0,
    "beta_5_8": "1/2",
    "beta_5_9": 0,
    "beta_6_8": "1/2",
    "beta_6_9": 0,
    "beta_7_8": "1/2",
    "beta_7_9": 0,
    "gamma": "1/2"
  },
  "min_freq_018": {
    "alpha": "5/2",
    "beta_0_8": 0,
    "beta_0_9": 0,
    "beta_1_8": 0,
    "beta_1_9": 0,
    "beta_2_8": 0,
    "beta_2_9": "5/2",
    "beta_3_8": 0,
    "beta_3_9": "5/2",
    "beta_4_8": "1/1",
    "beta_4_9": "3/2",
    "beta_5_8": "5/2",
    "beta_5_9": 0,
    "beta_6_8": "5/2",
    "beta_6_9": 0,
    "beta_7_8": 0,
    "beta_7_9": "5/2",
    "gamma": "11/2"
  },
  "max_freq_0": {
    "alpha": "1/1",
    "beta_0_8": 0,
    "beta_0_9": 0,
    "beta_1_8": 0,
    "beta_1_9": 0,
    "beta_2_8": 0,
    "beta_2_9": "1/1",
    "beta_3_8": 0,
    "beta_3_9": "1/1",
    "beta_4_8": "1/1",
    "beta_4_9": 0,
    "beta_5_8": 0,
    "beta_5_9": "1/1",
    "beta_6_8": "1/1",
    "beta_6_9": 0,
    "beta_7_8": "1/1",
    "beta_7_9": 0,
    "gamma": "2/1"
  },
  "max_freq_01": {
    "alpha": "1/1",
    "beta_0_8": 0,
    "beta_0_9": 0,
    "beta_1_8": 0,
    "beta_1_9": 0,
    "beta_2_8": 0,
    "beta_2_9": "1/1",
    "beta_3_8": 0,
    "beta_3_9": "1/1",
    "beta_4_8": "1/1",
    "beta_4_9": 0,
    "beta_5_8": 0,
    "beta_5_9": "1/1",
    "beta_6_8": "1/1",
    "beta_6_9": 0,
    "beta_7_8": "1/1",
    "beta_7_9": 0,
    "gamma": "2/1"
  },
  "max_freq_012": {
    "alpha": "3/2",
    "beta_0_8": 0,
    "beta_0_9": 0,
    "beta_1_8": 0,
    "beta_1_9": 0,
    "beta_2_8": 0,
    "beta_2_9": "3/2",
    "beta_3_8": "3/2",
    "beta_3_9": 0,
    "beta_4_8": 0,
    "beta_4_9": "3/2",
    "beta_5_8": 0,
    "beta_5_9": "3/2",
    "beta_6_8": "3/2",
    "beta_6_9": 0,
    "beta_7_8": "3/2",
    "beta_7_9": 0,
    "gamma": "3/1"
  },
  "max_freq_0123": {
    "alpha": "2/1",
    "beta_0_8": 0,
    "beta_0_9": 0,
    "beta_1_8": 0,
    "beta_1_9": 0,
    "beta_2_8": "2/1",
    "beta_2_9": 0,
    "beta_3_8": "2/1",
    "beta_3_9": 0,
    "beta_4_8": 0,
    "beta_4_9": "2/1",
    "beta_5_8": 0,
    "beta_5_9": "2/1",
    "beta_6_8": "2/1",
    "beta_6_9": 0,
    "beta_7_8": 0,
    "beta_7_9": "2/1",
    "gamma": "4/1"
  },
  "max_freq_01234": {
    "alpha": "5/2",
    "beta_0_8": 0,
    "beta_0_9": 0,
    "beta_1_8": 0,
    "beta_1_9": 0,
    "beta_2_8": "5/2",
    "beta_2_9": 0,
    "beta_3_8": "5/2",
    "beta_3_9": 0,
    "beta_4_8": 0,
    "beta_4_9": "5/2",
    "beta_5_8": 0,
    "beta_5_9": "5/2",
    "beta_6_8": 0,
    "beta_6_9": "5/2",
    "beta_7_8": "5/2",
    "beta_7_9": 0,
    "gamma": "5/1"
  },
  "max_freq_012345": {
    "alpha": "3/1",
    "beta_0_8": 0,
    "beta_0_9": 0,
    "beta_1_8": 0,
    "beta_1_9": 0,
    "beta_2_8": "3/1",
    "beta_2_9": 0,
    "beta_3_8": 0,
    "beta_3_9": "3/1",
    "beta_4_8": "3/1",
    "beta_4_9": 0,
    "beta_5_8": "3/1",
    "beta_5_9": 0,
    "beta_6_8": 0,
    "beta_6_9": "3/1",
    "beta_7_8": 0,
    "beta_7_9": "3/1",
    "gamma": "6/1"
  },
  "max_freq_0123456": {
    "alpha": "7/2",
    "beta_0_8": 0,
    "beta_0_9": 0,
    "beta_1_8": 0,
    "beta_1_9": 0,
    "beta_2_8": "7/2",
    "beta_2_9": 0,
    "beta_3_8": "7/2",
    "beta_3_9": 0,
    "beta_4_8": 0,
    "beta_4_9": "7/2",
    "beta_5_8": 0,
    "beta_5_9": "7/2",
    "beta_6_8": 0,
    "beta_6_9": "7/2",
    "beta_7_8": "7/2",
    "beta_7_9": 0,
    "gamma": "7/1"
  },
  "max_freq_01234567": {
    "alpha": "4/1",
    "beta_0_8": 0,
    "beta_0_9": 0,
    "beta_1_8": 0,
    "beta_1_9": 0,
    "beta_2_8": 0,
    "beta_2_9": "4/1",
    "beta_3_8": "4/1",
    "beta_3_9": 0,
    "beta_4_8": 0,
    "beta_4_9": "4/1",
    "beta_5_8": 0,
    "beta_5_9": "4/1",
    "beta_6_8": "4/1",
    "beta_6_9": 0,
    "beta_7_8": "4/1",
    "beta_7_9": 0,
    "gamma": "8/1"
  },
  "max_freq_012345678": {
    "alpha": "8/5",
    "beta_0_8": 0,
    "beta_0_9": 0,
    "beta_1_8": 0,
    "beta_1_9": 0,
    "beta_2_8": 0,
    "beta_2_9": "8/5",
    "beta_3_8": 0,
    "beta_3_9": "8/5",
    "beta_4_8": "8/5",
    "beta_4_9": 0,
    "beta_5_8": "8/5",
    "beta_5_9": 0,
    "beta_6_8": "8/5",
    "beta_6_9": 0,
    "beta_7_8": 0,
    "beta_7_9": "8/5",
    "gamma": "16/5"
  },
  "max_freq_01234568": {
    "alpha": "7/5",
    "beta_0_8": 0,
    "beta_0_9": 0,
    "beta_1_8": 0,
    "beta_1_9": 0,
    "beta_2_8": 0,
    "beta_2_9": "7/5",
    "beta_3_8": "7/5",
    "beta_3_9": 0,
    "beta_4_8": 0,
    "beta_4_9": "7/5",
    "beta_5_8": "7/5",
    "beta_5_9": 0,
    "beta_6_8": "7/5",
    "beta_6_9": 0,
    "beta_7_8": 0,
    "beta_7_9": "7/5",
    "gamma": "14/5"
  },
  "max_freq_012345689": {
    "alpha": "8/9",
    "beta_0_8": 0,
    "beta_0_9": 0,
    "beta_1_8": 0,
    "beta_1_9": 0,
    "beta_2_8": "8/9",
    "beta_2_9": 0,
    "beta_3_8": 0,
    "beta_3_9": "8/9",
    "beta_4_8": "8/9",
    "beta_4_9": 0,
    "beta_5_8": 0,
    "beta_5_9": "8/9",
    "beta_6_8": 0,
    "beta_6_9": "8/9",
    "beta_7_8": "8/9",
    "beta_7_9": 0,
    "gamma": "16/9"
  },
  "max_freq_0123458": {
    "alpha": "6/5",
    "beta_0_8": 0,
    "beta_0_9": 0,
    "beta_1_8": 0,
    "beta_1_9": 0,
    "beta_2_8": "6/5",
    "beta_2_9": 0,
    "beta_3_8": 0,
    "beta_3_9": "6/5",
    "beta_4_8": "6/5",
    "beta_4_9": 0,
    "beta_5_8": "6/5",
    "beta_5_9": 0,
    "beta_6_8": 0,
    "beta_6_9": "6/5",
    "beta_7_8": 0,
    "beta_7_9": "6/5",
    "gamma": "12/5"
  },
  "max_freq_01234589": {
    "alpha": "7/9",
    "beta_0_8": 0,
    "beta_0_9": 0,
    "beta_1_8": 0,
    "beta_1_9": 0,
    "beta_2_8": "7/9",
    "beta_2_9": 0,
    "beta_3_8": "7/9",
    "beta_3_9": 0,
    "beta_4_8": "7/9",
    "beta_4_9": 0,
    "beta_5_8": 0,
    "beta_5_9": "7/9",
    "beta_6_8": 0,
    "beta_6_9": "7/9",
    "beta_7_8": 0,
    "beta_7_9": "7/9",
    "gamma": "14/9"
  },
  "max_freq_012348": {
    "alpha": "30/29",
    "beta_0_8": 0,
    "beta_0_9": 0,
    "beta_1_8": 0,
    "beta_1_9": 0,
    "beta_2_8": 0,
    "beta_2_9": "30/29",
    "beta_3_8": "30/29",
    "beta_3_9": 0,
    "beta_4_8": "30/29",
    "beta_4_9": 0,
    "beta_5_8": 0,
    "beta_5_9": "30/29",
    "beta_6_8": 0,
    "beta_6_9": "30/29",
    "beta_7_8": "30/29",
    "beta_7_9": 0,
    "gamma": "60/29"
  },
  "max_freq_0123489": {
    "alpha": "2/3",
    "beta_0_8": 0,
    "beta_0_9": 0,
    "beta_1_8": 0,
    "beta_1_9": 0,
    "beta_2_8": "2/3",
    "beta_2_9": 0,
    "beta_3_8": "2/3",
    "beta_3_9": 0,
    "beta_4_8": 0,
    "beta_4_9": "2/3",
    "beta_5_8": 0,
    "beta_5_9": "2/3",
    "beta_6_8": 0,
    "beta_6_9": "2/3",
    "beta_7_8": "2/3",
    "beta_7_9": 0,
    "gamma": "4/3"
  },
  "max_freq_01238": {
    "alpha": "20/23",
    "beta_0_8": 0,
    "beta_0_9": 0,
    "beta_1_8": 0,
    "beta_1_9": 0,
    "beta_2_8": "20/23",
    "beta_2_9": 0,
    "beta_3_8": 0,
    "beta_3_9": "20/23",
    "beta_4_8": "20/23",
    "beta_4_9": 0,
    "beta_5_8": "20/23",
    "beta_5_9": 0,
    "beta_6_8": 0,
    "beta_6_9": "20/23",
    "beta_7_8": 0,
    "beta_7_9": "20/23",
    "gamma": "40/23"
  },
  "max_freq_012389": {
    "alpha": "5/9",
    "beta_0_8": 0,
    "beta_0_9": 0,
    "beta_1_8": 0,
    "beta_1_9": 0,
    "beta_2_8": 0,
    "beta_2_9": "5/9",
    "beta_3_8": "5/9",
    "beta_3_9": 0,
    "beta_4_8": "5/9",
    "beta_4_9": 0,
    "beta_5_8": "5/9",
    "beta_5_9": 0,
    "beta_6_8": 0,
    "beta_6_9": "5/9",
    "beta_7_8": 0,
    "beta_7_9": "5/9",
    "gamma": "10/9"
  },
  "max_freq_0128": {
    "alpha": "2/3",
    "beta_0_8": 0,
    "beta_0_9": 0,
    "beta_1_8": 0,
    "beta_1_9": 0,
    "beta_2_8": "2/3",
    "beta_2_9": 0,
    "beta_3_8": "2/3",
    "beta_3_9": 0,
    "beta_4_8": "2/3",
    "beta_4_9": 0,
    "beta_5_8": 0,
    "beta_5_9": "2/3",
    "beta_6_8": 0,
    "beta_6_9": "2/3",
    "beta_7_8": 0,
    "beta_7_9": "2/3",
    "gamma": "4/3"
  },
  "max_freq_01289": {
    "alpha": "4/1",
    "beta_0_8": 0,
    "beta_0_9": 0,
    "beta_1_8": 0,
    "beta_1_9": 0,
    "beta_2_8": 0,
    "beta_2_9": "4/1",
    "beta_3_8": 0,
    "beta_3_9": "4/1",
    "beta_4_8": "4/1",
    "beta_4_9": 0,
    "beta_5_8": "4/1",
    "beta_5_9": 0,
    "beta_6_8": "4/1",
    "beta_6_9": 0,
    "beta_7_8": 0,
    "beta_7_9": "4/1",
    "gamma": "8/1"
  },
  "max_freq_0189": {
    "alpha": "1/1",
    "beta_0_8": 0,
    "beta_0_9": 0,
    "beta_1_8": 0,
    "beta_1_9": 0,
    "beta_2_8": 0,
    "beta_2_9": "1/1",
    "beta_3_8": 0,
    "beta_3_9": "1/1",
    "beta_4_8": "1/1",
    "beta_4_9": 0,
    "beta_5_8": 0,
    "beta_5_9": "1/1",
    "beta_6_8": "1/1",
    "beta_6_9": 0,
    "beta_7_8": "1/1",
    "beta_7_9": 0,
    "gamma": "2/1"
  },
  "max_freq_02": {
    "alpha": "2/1",
    "beta_0_8": 0,
    "beta_0_9": 0,
    "beta_1_8": 0,
    "beta_1_9": 0,
    "beta_2_8": 0,
    "beta_2_9": "2/1",
    "beta_3_8": "2/1",
    "beta_3_9": 0,
    "beta_4_8": 0,
    "beta_4_9": "2/1",
    "beta_5_8": 0,
    "beta_5_9": "2/1",
    "beta_6_8": "2/1",
    "beta_6_9": 0,
    "beta_7_8": "2/1",
    "beta_7_9": 0,
    "gamma": "4/1"
  },
  "max_freq_023": {
    "alpha": "3/1",
    "beta_0_8": 0,
    "beta_0_9": 0,
    "beta_1_8": 0,
    "beta_1_9": 0,
    "beta_2_8": "3/1",
    "beta_2_9": 0,
    "beta_3_8": 0,
    "beta_3_9": "3/1",
    "beta_4_8": 0,
    "beta_4_9": "3/1",
    "beta_5_8": 0,
    "beta_5_9": "3/1",
    "beta_6_8": "3/1",
    "beta_6_9": 0,
    "beta_7_8": "3/1",
    "beta_7_9": 0,
    "gamma": "6/1"
  },
  "max_freq_0234": {
    "alpha": "4/1",
    "beta_0_8": 0,
    "beta_0_9": 0,
    "beta_1_8": 0,
    "beta_1_9": 0,
    "beta_2_8": 0,
    "beta_2_9": "4/1",
    "beta_3_8": "4/1",
    "beta_3_9": 0,
    "beta_4_8": "4/1",
    "beta_4_9": 0,
    "beta_5_8": 0,
    "beta_5_9": "4/1",
    "beta_6_8": 0,
    "beta_6_9": "4/1",
    "beta_7_8": "4/1",
    "beta_7_9": 0,
    "gamma": "8/1"
  },
  "max_freq_02345": {
    "alpha": "5/1",
    "beta_0_8": 0,
    "beta_0_9": 0,
    "beta_1_8": 0,
    "beta_1_9": 0,
    "beta_2_8": "5/1",
    "beta_2_9": 0,
    "beta_3_8": 0,
    "beta_3_9": "5/1",
    "beta_4_8": "5/1",
    "beta_4_9": 0,
    "beta_5_8": "5/1",
    "beta_5_9": 0,
    "beta_6_8": 0,
    "beta_6_9": "5/1",
    "beta_7_8": 0,
    "beta_7_9": "5/1",
    "gamma": "10/1"
  },
  "max_freq_023456": {
    "alpha": "6/1",
    "beta_0_8": 0,
    "beta_0_9": 0,
    "beta_1_8": 0,
    "beta_1_9": 0,
    "beta_2_8": 0,
    "beta_2_9": "6/1",
    "beta_3_8": "6/1",
    "beta_3_9": 0,
    "beta_4_8": 0,
    "beta_4_9": "6/1",
    "beta_5_8": "6/1",
    "beta_5_9": 0,
    "beta_6_8": "6/1",
    "beta_6_9": 0,
    "beta_7_8": 0,
    "beta_7_9": "6/1",
    "gamma": "12/1"
  },
  "max_freq_0234567": {
    "alpha": "7/1",
    "beta_0_8": 0,
    "beta_0_9": 0,
    "beta_1_8": 0,
    "beta_1_9": 0,
    "beta_2_8": 0,
    "beta_2_9": "7/1",
    "beta_3_8": "7/1",
    "beta_3_9": 0,
    "beta_4_8": 0,
    "beta_4_9": "7/1",
    "beta_5_8": "7/1",
    "beta_5_9": 0,
    "beta_6_8": "7/1",
    "beta_6_9": 0,
    "beta_7_8": 0,
    "beta_7_9": "7/1",
    "gamma": "14/1"
  },
  "max_freq_02345678": {
    "alpha": "7/4",
    "beta_0_8": 0,
    "beta_0_9": 0,
    "beta_1_8": 0,
    "beta_1_9": 0,
    "beta_2_8": "7/4",
    "beta_2_9": 0,
    "beta_3_8": 0,
    "beta_3_9": "7/4",
    "beta_4_8": 0,
    "beta_4_9": "7/4",
    "beta_5_8": 0,
    "beta_5_9": "7/4",
    "beta_6_8": "7/4",
    "beta_6_9": 0,
    "beta_7_8": "7/4",
    "beta_7_9": 0,
    "gamma": "7/2"
  },
  "max_freq_023456789": {
    "alpha": "1/1",
    "beta_0_8": 0,
    "beta_0_9": 0,
    "beta_1_8": 0,
    "beta_1_9": 0,
    "beta_2_8": 0,
    "beta_2_9": "1/1",
    "beta_3_8": 0,
    "beta_3_9": "1/1",
    "beta_4_8": "1/1",
    "beta_4_9": 0,
    "beta_5_8": "1/1",
    "beta_5_9": 0,
    "beta_6_8": "1/1",
    "beta_6_9": 0,
    "beta_7_8": 0,
    "beta_7_9": "1/1",
    "gamma": "2/1"
  },
  "max_freq_0234568": {
    "alpha": "3/2",
    "beta_0_8": 0,
    "beta_0_9": 0,
    "beta_1_8": 0,
    "beta_1_9": 0,
    "beta_2_8": 0,
    "beta_2_9": "3/2",
    "beta_3_8": "3/2",
    "beta_3_9": 0,
    "beta_4_8": 0,
    "beta_4_9": "3/2",
    "beta_5_8": "3/2",
    "beta_5_9": 0,
    "beta_6_8": "3/2",
    "beta_6_9": 0,
    "beta_7_8": 0,
    "beta_7_9": "3/2",
    "gamma": "3/1"
  },
  "max_freq_02345689": {
    "alpha": "7/8",
    "beta_0_8": 0,
    "beta_0_9": 0,
    "beta_1_8": 0,
    "beta_1_9": 0,
    "beta_2_8": 0,
    "beta_2_9": "7/8",
    "beta_3_8": "7/8",
    "beta_3_9": 0,
    "beta_4_8": 0,
    "beta_4_9": "7/8",
    "beta_5_8": "7/8",
    "beta_5_9": 0,
    "beta_6_8": "7/8",
    "beta_6_9": 0,
    "beta_7_8": 0,
    "beta_7_9": "7/8",
    "gamma": "7/4"
  },
  "max_freq_023458": {
    "alpha": "5/4",
    "beta_0_8": 0,
    "beta_0_9": 0,
    "beta_1_8": 0,
    "beta_1_9": 0,
    "beta_2_8": "5/4",
    "beta_2_9": 0,
    "beta_3_8": 0,
    "beta_3_9": "5/4",
    "beta_4_8": "5/4",
    "beta_4_9": 0,
    "beta_5_8": "5/4",
    "beta_5_9": 0,
    "beta_6_8": 0,
    "beta_6_9": "5/4",
    "beta_7_8": 0,
    "beta_7_9": "5/4",
    "gamma": "5/2"
  },
  "max_freq_0234589": {
    "alpha": "3/4",
    "beta_0_8": 0,
    "beta_0_9": 0,
    "beta_1_8": 0,
    "beta_1_9": 0,
    "beta_2_8": "3/4",
    "beta_2_9": 0,
    "beta_3_8": "3/4",
    "beta_3_9": 0,
    "beta_4_8": "3/4",
    "beta_4_9": 0,
    "beta_5_8": 0,
    "beta_5_9": "3/4",
    "beta_6_8": 0,
    "beta_6_9": "3/4",
    "beta_7_8": 0,
    "beta_7_9": "3/4",
    "gamma": "3/2"
  },
  "max_freq_02348": {
    "alpha": "10/9",
    "beta_0_8": 0,
    "beta_0_9": 0,
    "beta_1_8": 0,
    "beta_1_9": 0,
    "beta_2_8": "10/9",
    "beta_2_9": 0,
    "beta_3_8": 0,
    "beta_3_9": "10/9",
    "beta_4_8": 0,
    "beta_4_9": "10/9",
    "beta_5_8": "10/9",
    "beta_5_9": 0,
    "beta_6_8": "10/9",
    "beta_6_9": 0,
    "beta_7_8": 0,
    "beta_7_9": "10/9",
    "gamma": "20/9"
  },
  "max_freq_023489": {
    "alpha": "5/8",
    "beta_0_8": 0,
    "beta_0_9": 0,
    "beta_1_8": 0,
    "beta_1_9": 0,
    "beta_2_8": 0,
    "beta_2_9": "5/8",
    "beta_3_8": 0,
    "beta_3_9": "5/8",
    "beta_4_8": "5/8",
    "beta_4_9": 0,
    "beta_5_8": "5/8",
    "beta_5_9": 0,
    "beta_6_8": "5/8",
    "beta_6_9": 0,
    "beta_7_8": 0,
    "beta_7_9": "5/8",
    "gamma": "5/4"
  },
  "max_freq_0238": {
    "alpha": "6/7",
    "beta_0_8": 0,
    "beta_0_9": 0,
    "beta_1_8": 0,
    "beta_1_9": 0,
    "beta_2_8": "6/7",
    "beta_2_9": 0,
    "beta_3_8": 0,
    "beta_3_9": "6/7",
    "beta_4_8": "6/7",
    "beta_4_9": 0,
    "beta_5_8": "6/7",
    "beta_5_9": 0,
    "beta_6_8": 0,
    "beta_6_9": "6/7",
    "beta_7_8": 0,
    "beta_7_9": "6/7",
    "gamma": "12/7"
  },
  "max_freq_02389": {
    "alpha": "1/2",
    "beta_0_8": 0,
    "beta_0_9": 0,
    "beta_1_8": 0,
    "beta_1_9": 0,
    "beta_2_8": "1/2",
    "beta_2_9": 0,
    "beta_3_8": "1/2",
    "beta_3_9": 0,
    "beta_4_8": 0,
    "beta_4_9": "1/2",
    "beta_5_8": 0,
    "beta_5_9": "1/2",
    "beta_6_8": "1/2",
    "beta_6_9": 0,
    "beta_7_8": 0,
    "beta_7_9": "1/2",
    "gamma": "1/1"
  },
  "max_freq_028": {
    "alpha": "3/5",
    "beta_0_8": 0,
    "beta_0_9": 0,
    "beta_1_8": 0,
    "beta_1_9": 0,
    "beta_2_8": "3/5",
    "beta_2_9": 0,
    "beta_3_8": 0,
    "beta_3_9": "3/5",
    "beta_4_8": 0,
    "beta_4_9": "3/5",
    "beta_5_8": "3/5",
    "beta_5_9": 0,
    "beta_6_8": "3/5",
    "beta_6_9": 0,
    "beta_7_8": 0,
    "beta_7_9": "3/5",
    "gamma": "6/5"
  },
  "max_freq_0289": {
    "alpha": "3/2",
    "beta_0_8": 0,
    "beta_0_9": 0,
    "beta_1_8": 0,
    "beta_1_9": 0,
    "beta_2_8": 0,
    "beta_2_9": "3/2",
    "beta_3_8": 0,
    "beta_3_9": "3/2",
    "beta_4_8": "3/2",
    "beta_4_9": 0,
    "beta_5_8": "3/2",
    "beta_5_9": 0,
    "beta_6_8": 0,
    "beta_6_9": "3/2",
    "beta_7_8": "3/2",
    "beta_7_9": 0,
    "gamma": "3/1"
  },
  "max_freq_08": {
    "alpha": "2/1",
    "beta_0_8": 0,
    "beta_0_9": 0,
    "beta_1_8": 0,
    "beta_1_9": 0,
    "beta_2_8": 0,
    "beta_2_9": "2/1",
    "beta_3_8": "2/1",
    "beta_3_9": 0,
    "beta_4_8": "2/1",
    "beta_4_9": 0,
    "beta_5_8": 0,
    "beta_5_9": "2/1",
    "beta_6_8": 0,
    "beta_6_9": "2/1",
    "beta_7_8": "2/1",
    "beta_7_9": 0,
    "gamma": "4/1"
  },
  "max_freq_089": {
    "alpha": "1/2",
    "beta_0_8": 0,
    "beta_0_9": 0,
    "beta_1_8": 0,
    "beta_1_9": 0,
    "beta_2_8": 0,
    "beta_2_9": "1/2",
    "beta_3_8": "1/2",
    "beta_3_9": 0,
    "beta_4_8": "1/2",
    "beta_4_9": 0,
    "beta_5_8": "1/2",
    "beta_5_9": 0,
    "beta_6_8": 0,
    "beta_6_9": "1/2",
    "beta_7_8": 0,
    "beta_7_9": "1/2",
    "gamma": "1/1"
  },
  "max_freq_2345678": {
    "alpha": "2/1",
    "beta_0_8": 0,
    "beta_0_9": 0,
    "beta_1_8": 0,
    "beta_1_9": 0,
    "beta_2_8": "2/1",
    "beta_2_9": 0,
    "beta_3_8": 0,
    "beta_3_9": "2/1",
    "beta_4_8": 0,
    "beta_4_9": "2/1",
    "beta_5_8": 0,
    "beta_5_9": "2/1",
    "beta_6_8": "2/1",
    "beta_6_9": 0,
    "beta_7_8": "2/1",
    "beta_7_9": 0,
    "gamma": "4/1"
  },
  "max_freq_23456789": {
    "alpha": "1/1",
    "beta_0_8": 0,
    "beta_0_9": 0,
    "beta_1_8": 0,
    "beta_1_9": 0,
    "beta_2_8": 0,
    "beta_2_9": "1/1",
    "beta_3_8": 0,
    "beta_3_9": "1/1",
    "beta_4_8": "1/1",
    "beta_4_9": 0,
    "beta_5_8": "1/1",
    "beta_5_9": 0,
    "beta_6_8": "1/1",
    "beta_6_9": 0,
    "beta_7_8": 0,
    "beta_7_9": "1/1",
    "gamma": "2/1"
  },
  "max_freq_234568": {
    "alpha": "30/17",
    "beta_0_8": 0,
    "beta_0_9": 0,
    "beta_1_8": 0,
    "beta_1_9": 0,
    "beta_2_8": "30/17",
    "beta_2_9": 0,
    "beta_3_8": 0,
    "beta_3_9": "30/17",
    "beta_4_8": "30/17",
    "beta_4_9": 0,
    "beta_5_8": 0,
    "beta_5_9": "30/17",
    "beta_6_8": 0,
    "beta_6_9": "30/17",
    "beta_7_8": "30/17",
    "beta_7_9": 0,
    "gamma": "60/17"
  },
  "max_freq_2345689": {
    "alpha": "6/7",
    "beta_0_8": 0,
    "beta_0_9": 0,
    "beta_1_8": 0,
    "beta_1_9": 0,
    "beta_2_8": 0,
    "beta_2_9": "6/7",
    "beta_3_8": "6/7",
    "beta_3_9": 0,
    "beta_4_8": 0,
    "beta_4_9": "6/7",
    "beta_5_8": "6/7",
    "beta_5_9": 0,
    "beta_6_8": "6/7",
    "beta_6_9": 0,
    "beta_7_8": 0,
    "beta_7_9": "6/7",
    "gamma": "12/7"
  },
  "max_freq_23458": {
    "alpha": "20/13",
    "beta_0_8": 0,
    "beta_0_9": 0,
    "beta_1_8": 0,
    "beta_1_9": 0,
    "beta_2_8": 0,
    "beta_2_9": "20/13",
    "beta_3_8": "20/13",
    "beta_3_9": 0,
    "beta_4_8": 0,
    "beta_4_9": "20/13",
    "beta_5_8": 0,
    "beta_5_9": "20/13",
    "beta_6_8": "20/13",
    "beta_6_9": 0,
    "beta_7_8": "20/13",
    "beta_7_9": 0,
    "gamma": "40/13"
  },
  "max_freq_234589": {
    "alpha": "5/7",
    "beta_0_8": 0,
    "beta_0_9": 0,
    "beta_1_8": 0,
    "beta_1_9": 0,
    "beta_2_8": 0,
    "beta_2_9": "5/7",
    "beta_3_8": 0,
    "beta_3_9": "5/7",
    "beta_4_8": 0,
    "beta_4_9": "5/7",
    "beta_5_8": "5/7",
    "beta_5_9": 0,
    "beta_6_8": "5/7",
    "beta_6_9": 0,
    "beta_7_8": "5/7",
    "beta_7_9": 0,
    "gamma": "10/7"
  },
  "max_freq_2348": {
    "alpha": "6/5",
    "beta_0_8": 0,
    "beta_0_9": 0,
    "beta_1_8": 0,
    "beta_1_9": 0,
    "beta_2_8": "6/5",
    "beta_2_9": 0,
    "beta_3_8": 0,
    "beta_3_9": "6/5",
    "beta_4_8": 0,
    "beta_4_9": "6/5",
    "beta_5_8": "6/5",
    "beta_5_9": 0,
    "beta_6_8": "6/5",
    "beta_6_9": 0,
    "beta_7_8": 0,
    "beta_7_9": "6/5",
    "gamma": "12/5"
  },
  "max_freq_23489": {
    "alpha": "4/7",
    "beta_0_8": 0,
    "beta_0_9": 0,
    "beta_1_8": 0,
    "beta_1_9": 0,
    "beta_2_8": 0,
    "beta_2_9": "4/7",
    "beta_3_8": "4/7",
    "beta_3_9": 0,
    "beta_4_8": "4/7",
    "beta_4_9": 0,
    "beta_5_8": 0,
    "beta_5_9": "4/7",
    "beta_6_8": 0,
    "beta_6_9": "4/7",
    "beta_7_8": "4/7",
    "beta_7_9": 0,
    "gamma": "8/7"
  },
  "max_freq_238": {
    "alpha": "3/4",
    "beta_0_8": 0,
    "beta_0_9": 0,
    "beta_1_8": 0,
    "beta_1_9": 0,
    "beta_2_8": "3/4",
    "beta_2_9": 0,
    "beta_3_8": "3/4",
    "beta_3_9": 0,
    "beta_4_8": 0,
    "beta_4_9": "3/4",
    "beta_5_8": 0,
    "beta_5_9": "3/4",
    "beta_6_8": "3/4",
    "beta_6_9": 0,
    "beta_7_8": 0,
    "beta_7_9": "3/4",
    "gamma": "3/2"
  },
  "max_freq_2389": {
    "alpha": "3/7",
    "beta_0_8": 0,
    "beta_0_9": 0,
    "beta_1_8": 0,
    "beta_1_9": 0,
    "beta_2_8": 0,
    "beta_2_9": "3/7",
    "beta_3_8": 0,
    "beta_3_9": "3/7",
    "beta_4_8": "3/7",
    "beta_4_9": 0,
    "beta_5_8": "3/7",
    "beta_5_9": 0,
    "beta_6_8": 0,
    "beta_6_9": "3/7",
    "beta_7_8": "3/7",
    "beta_7_9": 0,
    "gamma": "6/7"
  },
  "max_freq_28": {
    "alpha": "1/2",
    "beta_0_8": 0,
    "beta_0_9": 0,
    "beta_1_8": 0,
    "beta_1_9": 0,
    "beta_2_8": "1/2",
    "beta_2_9": 0,
    "beta_3_8": 0,
    "beta_3_9": "1/2",
    "beta_4_8": 0,
    "beta_4_9": "1/2",
    "beta_5_8": 0,
    "beta_5_9": "1/2",
    "beta_6_8": "1/2",
    "beta_6_9": 0,
    "beta_7_8": "1/2",
    "beta_7_9": 0,
    "gamma": "1/1"
  },
  "max_freq_289": {
    "alpha": "2/3",
    "beta_0_8": 0,
    "beta_0_9": 0,
    "beta_1_8": 0,
    "beta_1_9": 0,
    "beta_2_8": "2/3",
    "beta_2_9": 0,
    "beta_3_8": 0,
    "beta_3_9": "2/3",
    "beta_4_8": "2/3",
    "beta_4_9": 0,
    "beta_5_8": "2/3",
    "beta_5_9": 0,
    "beta_6_8": 0,
    "beta_6_9": "2/3",
    "beta_7_8": 0,
    "beta_7_9": "2/3",
    "gamma": "4/3"
  },
  "max_freq_8": {
    "alpha": "1/2",
    "beta_0_8": 0,
    "beta_0_9": 0,
    "beta_1_8": 0,
    "beta_1_9": 0,
    "beta_2_8": 0,
    "beta_2_9": "1/2",
    "beta_3_8": 0,
    "beta_3_9": "1/2",
    "beta_4_8": "1/2",
    "beta_4_9": 0,
    "beta_5_8": "1/2",
    "beta_5_9": 0,
    "beta_6_8": 0,
    "beta_6_9": "1/2",
    "beta_7_8": "1/2",
    "beta_7_9": 0,
    "gamma": "1/1"
  },
  "max_freq_89": {
    "alpha": "1/5",
    "beta_0_8": 0,
    "beta_0_9": 0,
    "beta_1_8": 0,
    "beta_1_9": 0,
    "beta_2_8": "1/5",
    "beta_2_9": 0,
    "beta_3_8": "1/5",
    "beta_3_9": 0,
    "beta_4_8": 0,
    "beta_4_9": "1/5",
    "beta_5_8": 0,
    "beta_5_9": "1/5",
    "beta_6_8": "1/5",
    "beta_6_9": 0,
    "beta_7_8": 0,
    "beta_7_9": "1/5",
    "gamma": "2/5"
  },
  "max_marginal_2": {
    "alpha": 0,
    "beta_0_8": 0,
    "beta_0_9": 0,
    "beta_1_8": 0,
    "beta_1_9": 0,
    "beta_2_8": "1/2",
    "beta_2_9": "1/2",
    "beta_3_8": 0,
    "beta_3_9": 0,
    "beta_4_8": 0,
    "beta_4_9": 0,
    "beta_5_8": 0,
    "beta_5_9": 0,
    "beta_6_8": 0,
    "beta_6_9": 0,
    "beta_7_8": 0,
    "beta_7_9": 0,
    "gamma": "1/6"
  },
  "min_marginal_2": {
    "alpha": "1/1",
    "beta_0_8": 0,
    "beta_0_9": 0,
    "beta_1_8": 0,
    "beta_1_9": 0,
    "beta_2_8": 0,
    "beta_2_9": 0,
    "beta_3_8": 0,
    "beta_3_9": "1/1",
    "beta_4_8": 0,
    "beta_4_9": "1/1",
    "beta_5_8": "1/2",
    "beta_5_9": "1/2",
    "beta_6_8": "1/1",
    "beta_6_9": 0,
    "beta_7_8": "1/1",
    "beta_7_9": 0,
    "gamma": "11/6"
  }
}